{
  "Kzarka":{
      "name":"Kzarka",
      "color":13369344,
      "description":"The Lord of Corruption",
      "location":"Serendia Shrine",
      "recommendations":"lvl 56\n150 AP\n180 DP",
      "avatar":"https://i.imgur.com/KoGfDQT.png",
      "drops":"Kzarka's Sealed Weapon Box\nBelongings of an Adventurer",
      "link":"https://docs.google.com/document/d/19O-Ons2uvSkUGawncm9xE2LhcfgEAZ5qsE0_ZhnlzTo/edit#heading=h.2vx6ipz0xdwu"
    },
  "Karanda":{
      "name":"Karanda",
      "description":"Harpy Queen",
      "color":45746,
      "location":"Karanda Ridge",
      "recommendations":"lvl 56\n150 AP\n180 DP",
      "avatar":"https://i.imgur.com/eNfGAqu.png",
      "drops":"Dandelion Weapon Box\nBelongings of an Adventurer",
      "link":"https://docs.google.com/document/d/19O-Ons2uvSkUGawncm9xE2LhcfgEAZ5qsE0_ZhnlzTo/edit#heading=h.2vx6ipz0xdwu"
    },
  "Kutum":{
      "name":"Kutum",
      "description":"An ancient life form by the name of Kutum",
      "color":5832793,
      "location":"Scarlet Sand Chamber",
      "recommendations":"lvl 56\n150 AP\n180 DP",
      "avatar":"https://i.imgur.com/W15TFlL.png",
      "drops":"Kutum's Sealed Sub-weapon Box\nBelongings of an Adventurer",
      "link":"https://docs.google.com/document/d/19O-Ons2uvSkUGawncm9xE2LhcfgEAZ5qsE0_ZhnlzTo/edit#heading=h.2vx6ipz0xdwu"
    },
  "Nouver":{
      "name":"Nouver",
      "description":"A dragon hiding in a sandstorm",
      "color":13413376,
      "location":"Great Desert of Valencia",
      "recommendations":"lvl 56\n150 AP\n180 DP",
      "avatar":"https://i.imgur.com/iwnyMxt.png",
      "drops":"Nouver's Sealed Sub-weapon Box\nBelongings of an Adventurer",
      "link":"https://docs.google.com/document/d/19O-Ons2uvSkUGawncm9xE2LhcfgEAZ5qsE0_ZhnlzTo/edit#heading=h.2vx6ipz0xdwu"
    },
  "Vell":{
      "name":"Vell",
      "description":"The Heart of the Ocean",
      "color":58853,
      "location":"Vell's Realm",
      "recommendations":"lvl 56\n150 AP\n180 DP\na Ship (Bartali Sailboat or higher)",
      "avatar":"https://i.imgur.com/nmxjEyV.png",
      "drops":"Vell's Heart\nVell's Concentrated Magic",
      "link":"https://docs.google.com/document/d/19O-Ons2uvSkUGawncm9xE2LhcfgEAZ5qsE0_ZhnlzTo/edit#heading=h.2vx6ipz0xdwu"
    },
  "Quint":{
      "name":"Quint",
      "description":"The First Troll",
      "color":7566195,
      "location":"Quint Hill",
      "recommendations":"lvl 56\n150 AP\n180 DP",
      "avatar":"https://i.imgur.com/HLSHnRp.png",
      "drops":"Belongings of an Adventurer",
      "link":"https://docs.google.com/document/d/19O-Ons2uvSkUGawncm9xE2LhcfgEAZ5qsE0_ZhnlzTo/edit#heading=h.2vx6ipz0xdwu"
    },
  "Muraka":{
      "name":"Muraka",
      "description":"The King of Ogres",
      "color":39168,
      "location":"Mansha Forest",
      "recommendations":"lvl 56\n150 AP\n180 DP",
      "avatar":"https://i.imgur.com/ZoGFtCI.png",
      "drops":"Belongings of an Adventurer",
      "link":"https://docs.google.com/document/d/19O-Ons2uvSkUGawncm9xE2LhcfgEAZ5qsE0_ZhnlzTo/edit#heading=h.2vx6ipz0xdwu"
    },
  "Garmoth":{
      "name":"Garmoth",
      "description":"The Crimson Dragon",
      "color":13403136,
      "location":"Garmoth's Nest",
      "recommendations":"lvl 56\n150 AP\n250 DP",
      "avatar":"https://i.imgur.com/2MUA1dn.png",
      "drops":"Garmoth's Heart\nGarmoth's Horn\nCaphras Stone Bundle\nCombined Magic Crystal - Gervish/Hoom/Macalod\nBelongings of an Adventurer",
      "link":"https://docs.google.com/document/d/19O-Ons2uvSkUGawncm9xE2LhcfgEAZ5qsE0_ZhnlzTo/edit#heading=h.2vx6ipz0xdwu"
    },
  "Offin":{
      "name":"Offin",
      "description":"Mirumok Destroyer",
      "color":16777087,
      "location":"Holo Forest",
      "recommendations":"lvl 56\n150 AP\n250 DP\n*Getting killed by Offin will result in loss of XP and Crystals*",
      "avatar":"https://i.imgur.com/zFuKRZt.png",
      "drops":"Offin Tet's Light Sealed Weapon Box\nValtarra Eclipsed Belt\nJIN/BON/WON Magic Crystal - Cobelinus",
      "link":"https://docs.google.com/document/d/19O-Ons2uvSkUGawncm9xE2LhcfgEAZ5qsE0_ZhnlzTo/edit#heading=h.2vx6ipz0xdwu"
    }
}